{"autoplayBgm":false,"autoplayBgs":false,"battleback1Name":"","battleback2Name":"","bgm":{"name":"","pan":0,"pitch":100,"volume":90},"bgs":{"name":"","pan":0,"pitch":100,"volume":90},"disableDashing":false,"displayName":"","encounterList":[],"encounterStep":30,"height":13,"note":"","parallaxLoopX":false,"parallaxLoopY":false,"parallaxName":"","parallaxShow":true,"parallaxSx":0,"parallaxSy":0,"scrollType":0,"specifyBattleback":false,"tilesetId":1,"width":17,"data":[0,0,0,0,0,0,0,0,0,0,0,0,0,0,0,0,0,0,0,0,0,0,0,0,0,0,0,0,0,0,0,0,0,0,0,0,0,0,0,0,0,0,0,0,0,0,0,0,0,0,0,0,0,0,0,0,0,0,0,0,0,0,0,0,0,0,0,0,0,0,0,0,0,0,0,0,0,0,0,0,0,0,0,0,0,0,0,0,0,0,0,0,0,0,0,0,0,0,0,0,0,0,0,0,0,0,0,0,0,0,1544,0,0,0,0,0,0,0,0,0,0,0,0,0,0,0,0,0,0,0,0,0,0,0,0,0,0,0,0,0,0,0,0,0,0,0,0,0,0,0,0,0,0,0,0,0,0,0,0,0,0,0,0,0,0,0,0,0,0,0,0,0,0,0,0,0,0,0,0,0,0,0,0,0,0,0,0,0,0,0,0,0,0,0,0,0,0,0,0,0,0,0,0,0,0,0,0,0,0,0,0,0,0,0,0,0,0,0,0,0,0,0,0,0,0,0,0,0,0,0,0,0,0,0,0,0,0,0,0,0,0,0,0,0,0,0,0,0,0,0,0,0,0,0,0,0,0,0,0,0,0,0,0,0,0,0,0,0,0,0,0,0,0,0,0,0,0,0,0,0,0,0,0,0,0,0,0,0,0,0,0,0,0,0,0,0,0,0,0,0,0,0,0,0,0,0,0,0,0,0,0,0,0,0,0,0,0,0,0,0,0,0,0,0,0,0,0,0,0,0,0,0,0,0,0,0,0,0,0,0,0,0,0,0,0,0,0,0,0,0,0,0,0,0,0,0,0,0,0,0,0,0,0,0,0,0,0,0,0,0,0,0,0,0,0,0,0,0,0,0,0,0,0,0,0,0,0,0,0,0,0,0,0,0,0,0,0,0,0,0,0,0,0,0,0,0,0,0,0,0,0,0,0,0,0,0,0,0,0,0,0,0,0,0,0,0,0,0,0,0,0,0,0,0,0,0,0,0,0,0,0,0,0,0,0,0,0,0,0,0,0,0,0,0,0,0,0,0,0,0,0,0,0,0,0,0,0,0,0,0,0,0,0,0,0,0,0,0,0,0,0,0,0,0,0,0,0,0,0,0,0,0,0,0,0,0,0,0,0,0,0,0,0,0,0,0,0,0,0,0,0,0,0,0,0,0,0,0,0,0,0,0,0,0,0,0,0,0,0,0,0,0,0,0,0,0,0,0,0,0,0,0,0,0,0,0,0,0,0,0,0,0,0,0,0,0,0,0,0,0,0,0,0,0,0,0,0,0,0,0,0,0,0,0,0,0,0,0,0,0,0,0,0,0,0,0,0,0,0,0,0,0,0,0,0,0,0,0,0,0,0,0,0,0,0,0,0,0,0,0,0,0,0,0,0,0,0,0,0,0,0,0,0,0,0,0,0,0,0,0,0,0,0,0,0,0,0,0,0,0,0,0,0,0,0,0,0,0,0,0,0,0,0,0,0,0,0,0,0,0,0,0,0,0,0,0,0,0,0,0,0,0,0,0,0,0,0,0,0,0,0,0,0,0,0,0,0,0,0,0,0,0,0,0,0,0,0,0,0,0,0,0,0,0,0,0,0,0,0,0,0,0,0,0,0,0,0,0,0,0,0,0,0,0,0,0,0,0,0,0,0,0,0,0,0,0,0,0,0,0,0,0,0,0,0,0,0,0,0,0,0,0,0,0,0,0,0,0,0,0,0,0,0,0,0,0,0,0,0,0,0,0,0,0,0,0,0,0,0,0,0,0,0,0,0,0,0,0,0,0,0,0,0,0,0,0,0,0,0,0,0,0,0,0,0,0,0,0,0,0,0,0,0,0,0,0,0,0,0,0,0,0,0,0,0,0,0,0,0,0,0,0,0,0,0,0,0,0,0,0,0,0,0,0,0,0,0,0,0,0,0,0,0,0,0,0,0,0,0,0,0,0,0,0,0,0,0,0,0,0,0,0,0,0,0,0,0,0,0,0,0,0,0,0,0,0,0,0,0,0,0,0,0,0,0,0,0,0,0,0,0,0,0,0,0,0,0,0,0,0,0,0,0,0,0,0,0,0,0,0,0,0,0,0,0,0,0,0,0,0,0,0,0,0,0,0,0,0,0,0,0,0,0,0,0,0,0,0,0,0,0,0,0,0,0,0,0,0,0,0,0,0,0,0,0,0,0,0,0,0,0,0,0,0,0,0,0,0,0,0,0,0,0,0,0,0,0,0,0,0,0,0,0,0,0,0,0,0,0,0,0,0,0,0,0,0,0,0,0,0,0,0,0,0,0,0,0,0,0,0,0,0,0,0,0,0,0,0,0,0,0,0,0,0,0,0,0,0,0,0,0,0,0,0,0,0,0,0,0,0,0,0,0,0,0,0,0,0,0,0,0,0,0,0,0,0,0,0,0,0,0,0,0,0,0,0,0,0,0,0,0,0,0,0,0,0,0,0,0,0,0,0,0,0,0,0,0,0,0,0,0,0,0,0,0,0,0,0,0,0,0,0,0,0,0,0,0,0,0,0,0,0,0,0,0,0,0,0,0,0,0,0,0,0,0,0,0,0,0,0,0,0,0,0,0,0,0,0,0,0,0,0,0,0,0,0,0,0,0,0,0,0,0,0,0,0,0,0,0,0,0,0,0,0,0,0,0,0,0,0,0,0,0,0,0,0,0,0,0,0,0,0,0,0,0,0,0,0,0,0,0,0,0,0,0,0,0,0,0,0,0,0,0,0,0,0,0,0,0,0,0,0,0,0,0,0,0,0,0,0,0,0,0,0,0,0,0,0,0,0,0,0,0,0,0,0,0,0,0,0,0,0,0,0,0,0,0,0,0,0,0,0,0,0,0,0,0,0,0,0,0,0,0,0,0,0,0,0,0,0,0,0,0,0,0,0,0,0,0,0,0,0,0,0,0,0,0,0,0,0,0,0,0,0,0,0,0,0,0,0,0,0,0,0,0,0,0,0,0,0,0,0,0,0,0,0],"events":[null,{"id":1,"name":"EV001","note":"","pages":[{"conditions":{"actorId":1,"actorValid":false,"itemId":1,"itemValid":false,"selfSwitchCh":"A","selfSwitchValid":false,"switch1Id":1,"switch1Valid":false,"switch2Id":1,"switch2Valid":false,"variableId":1,"variableValid":false,"variableValue":0},"directionFix":false,"image":{"characterIndex":0,"characterName":"","direction":2,"pattern":0,"tileId":0},"list":[{"code":231,"indent":0,"parameters":[1,"sousasetumei",0,0,0,0,100,100,255,0]},{"code":357,"indent":0,"parameters":["MessageWindowPopup","CHANGE_TAIL","テール画像変更",{"tailImage":"kuuhaku"}]},{"code":657,"indent":0,"parameters":["テール画像 = kuuhaku"]},{"code":357,"indent":0,"parameters":["MessageWindowPopup","POPUP_INVALID","フキダシ無効化",{}]},{"code":101,"indent":0,"parameters":["",0,2,2,""]},{"code":401,"indent":0,"parameters":[""]},{"code":221,"indent":0,"parameters":[]},{"code":230,"indent":0,"parameters":[60]},{"code":231,"indent":0,"parameters":[1,"chapter1",0,0,0,0,100,100,255,0]},{"code":222,"indent":0,"parameters":[]},{"code":241,"indent":0,"parameters":[{"name":"kodokunamonoro-gunotameni","volume":20,"pitch":100,"pan":0}]},{"code":101,"indent":0,"parameters":["",0,2,2,""]},{"code":401,"indent":0,"parameters":[""]},{"code":221,"indent":0,"parameters":[]},{"code":230,"indent":0,"parameters":[60]},{"code":235,"indent":0,"parameters":[1]},{"code":223,"indent":0,"parameters":[[-255,-255,0,255],60,true]},{"code":205,"indent":0,"parameters":[-1,{"list":[{"code":37,"indent":null},{"code":4,"indent":null},{"code":38,"indent":null},{"code":0}],"repeat":false,"skippable":false,"wait":true}]},{"code":505,"indent":0,"parameters":[{"code":37,"indent":null}]},{"code":505,"indent":0,"parameters":[{"code":4,"indent":null}]},{"code":505,"indent":0,"parameters":[{"code":38,"indent":null}]},{"code":222,"indent":0,"parameters":[]},{"code":245,"indent":0,"parameters":[{"name":"1_ame","volume":15,"pitch":50,"pan":0}]},{"code":236,"indent":0,"parameters":["rain",1,60,true]},{"code":357,"indent":0,"parameters":["LN_FilmicFilter","SetFilmicFilter","SetFilmicFilter",{"filterId":"0","duration":"30","wait":"true"}]},{"code":657,"indent":0,"parameters":["フィルタID = 0"]},{"code":657,"indent":0,"parameters":["時間 = 30"]},{"code":657,"indent":0,"parameters":["完了までウェイト = true"]},{"code":357,"indent":0,"parameters":["MessageWindowPopup","CHANGE_TAIL","テール画像変更",{"tailImage":"kuuhaku"}]},{"code":657,"indent":0,"parameters":["テール画像 = kuuhaku"]},{"code":357,"indent":0,"parameters":["MessageWindowPopup","POPUP_INVALID","フキダシ無効化",{}]},{"code":230,"indent":0,"parameters":[60]},{"code":101,"indent":0,"parameters":["",0,1,1,""]},{"code":401,"indent":0,"parameters":["\\ac――\\.得知父母去世的那天，"]},{"code":101,"indent":0,"parameters":["",0,1,1,""]},{"code":401,"indent":0,"parameters":["\\ac大雨滂沱。"]},{"code":230,"indent":0,"parameters":[30]},{"code":101,"indent":0,"parameters":["",0,1,1,""]},{"code":401,"indent":0,"parameters":["\\ac死因是，\\.交通事故。"]},{"code":230,"indent":0,"parameters":[30]},{"code":101,"indent":0,"parameters":["",0,1,1,""]},{"code":401,"indent":0,"parameters":["\\ac听到了电话留言，得知消息后，"]},{"code":401,"indent":0,"parameters":["\\ac我急忙赶到医院……"]},{"code":230,"indent":0,"parameters":[30]},{"code":101,"indent":0,"parameters":["",0,1,1,""]},{"code":401,"indent":0,"parameters":["\\ac但已经太迟了――"]},{"code":230,"indent":0,"parameters":[60]},{"code":101,"indent":0,"parameters":["",0,1,1,""]},{"code":401,"indent":0,"parameters":["\\ac我见到的是，已经死亡的父母，"]},{"code":401,"indent":0,"parameters":["\\ac没能见到他们的最后一面。"]},{"code":230,"indent":0,"parameters":[30]},{"code":101,"indent":0,"parameters":["",0,1,1,""]},{"code":401,"indent":0,"parameters":["\\ac…\\.…\\."]},{"code":401,"indent":0,"parameters":["\\ac…\\.…\\.…\\.…"]},{"code":230,"indent":0,"parameters":[60]},{"code":101,"indent":0,"parameters":["",0,1,1,""]},{"code":401,"indent":0,"parameters":["\\ac在未曾停息的雨中，只有我和殡葬公司的"]},{"code":401,"indent":0,"parameters":["\\ac工作人员，安静的举行了葬礼。"]},{"code":230,"indent":0,"parameters":[30]},{"code":101,"indent":0,"parameters":["",0,1,1,""]},{"code":401,"indent":0,"parameters":["\\ac因为二人生前的愿望就是，"]},{"code":401,"indent":0,"parameters":["\\ac\\.\\.\\.秘密地举行葬礼。"]},{"code":230,"indent":0,"parameters":[30]},{"code":101,"indent":0,"parameters":["",0,1,1,""]},{"code":401,"indent":0,"parameters":["\\ac父母在我很小的时候就和亲戚们断绝了来往，"]},{"code":401,"indent":0,"parameters":["\\ac听他们说过没有可以叫来参加葬礼的人。"]},{"code":230,"indent":0,"parameters":[60]},{"code":101,"indent":0,"parameters":["",0,1,1,""]},{"code":401,"indent":0,"parameters":["\\ac……雨音回响，这是一场非常安静的葬礼。"]},{"code":230,"indent":0,"parameters":[60]},{"code":230,"indent":0,"parameters":[30]},{"code":101,"indent":0,"parameters":["",0,1,1,""]},{"code":401,"indent":0,"parameters":["\\ac从始至终孤身一人站在宽阔葬礼仪式现场的我，"]},{"code":401,"indent":0,"parameters":["\\ac被无以言表的孤独感所侵袭。"]},{"code":101,"indent":0,"parameters":["",0,1,1,""]},{"code":401,"indent":0,"parameters":["\\ac无所依靠，"]},{"code":401,"indent":0,"parameters":["\\ac我感到前路暗淡无光。"]},{"code":230,"indent":0,"parameters":[30]},{"code":101,"indent":0,"parameters":["",0,1,1,""]},{"code":401,"indent":0,"parameters":["\\ac……"]},{"code":401,"indent":0,"parameters":["\\ac…………"]},{"code":230,"indent":0,"parameters":[60]},{"code":230,"indent":0,"parameters":[30]},{"code":101,"indent":0,"parameters":["",0,1,1,""]},{"code":401,"indent":0,"parameters":["\\ac……父母去世的那天。\\."]},{"code":401,"indent":0,"parameters":["\\ac竟然碰巧是我的生日。"]},{"code":101,"indent":0,"parameters":["",0,1,1,""]},{"code":401,"indent":0,"parameters":["\\ac一定也包含了"]},{"code":401,"indent":0,"parameters":["\\ac祝贺我升入大学的心情吧。"]},{"code":101,"indent":0,"parameters":["",0,1,1,""]},{"code":401,"indent":0,"parameters":["\\ac因为我被录取，而比我更开心的父母"]},{"code":401,"indent":0,"parameters":["\\ac应该非常喜出望外。"]},{"code":230,"indent":0,"parameters":[60]},{"code":101,"indent":0,"parameters":["",0,1,1,""]},{"code":401,"indent":0,"parameters":["\\ac从被撞坏的汽车中\\."]},{"code":401,"indent":0,"parameters":["\\ac发现的礼物，\\.\\.恰巧证明了这点。"]},{"code":221,"indent":0,"parameters":[]},{"code":201,"indent":0,"parameters":[0,3,4,9,0,0]},{"code":0,"indent":0,"parameters":[]}],"moveFrequency":3,"moveRoute":{"list":[{"code":0,"parameters":[]}],"repeat":true,"skippable":false,"wait":false},"moveSpeed":6,"moveType":0,"priorityType":0,"stepAnime":false,"through":false,"trigger":3,"walkAnime":true}],"x":16,"y":0}]}